sqlmix/__init__.py
sqlmix/async_.py
sqlmix/twisted.py
sqlmix-0.12.9.dist-info/COPYING
sqlmix-0.12.9.dist-info/METADATA
sqlmix-0.12.9.dist-info/WHEEL
sqlmix-0.12.9.dist-info/top_level.txt
sqlmix-0.12.9.dist-info/RECORD
